hybrid_attributes.py
hybrid_attributes-0.1.0.dist-info/DESCRIPTION.rst
hybrid_attributes-0.1.0.dist-info/METADATA
hybrid_attributes-0.1.0.dist-info/RECORD
hybrid_attributes-0.1.0.dist-info/WHEEL
hybrid_attributes-0.1.0.dist-info/metadata.json
hybrid_attributes-0.1.0.dist-info/top_level.txt
