Metadata-Version: 2.0
Name: hybrid-attributes
Version: 0.1.0
Summary: Hybrid attributes
Home-page: https://github.com/DasIch/hybrid-attributes/
Author: Daniel Neuhäuser
Author-email: ich@danielneuhaeuser.de
License: UNKNOWN
Platform: UNKNOWN
Classifier: License :: OSI Approved :: BSD License
Classifier: Programming Language :: Python :: 3.4
Classifier: Programming Language :: Python :: 3.5
Classifier: Programming Language :: Python :: Implementation :: CPython
